lima2/client/__init__.py
lima2/client/exceptions.py
lima2/client/py.typed
lima2/client/services.py
lima2/client/session.py
lima2/client/shell.py
lima2/common/__init__.py
lima2/common/exceptions.py
lima2/common/pipelines.py
lima2/common/progress_counter.py
lima2/common/py.typed
lima2/common/state.py
lima2/common/types.py
lima2/common/devencoded/__init__.py
lima2/common/devencoded/dense_frame.py
lima2/common/devencoded/exception.py
lima2/common/devencoded/smx_sparse_frame.py
lima2/common/devencoded/sparse_frame.py
lima2/common/devencoded/structured_array.py
lima2/conductor/__init__.py
lima2/conductor/acquisition.py
lima2/conductor/acquisition_system.py
lima2/conductor/detector.py
lima2/conductor/py.typed
lima2/conductor/topology.py
lima2/conductor/utils.py
lima2/conductor/processing/__init__.py
lima2/conductor/processing/failing.py
lima2/conductor/processing/legacy.py
lima2/conductor/processing/master_file.py
lima2/conductor/processing/pipeline.py
lima2/conductor/processing/reduced_data.py
lima2/conductor/processing/smx.py
lima2/conductor/processing/xpcs.py
lima2/conductor/tango/__init__.py
lima2/conductor/tango/container.py
lima2/conductor/tango/control.py
lima2/conductor/tango/processing.py
lima2/conductor/tango/receiver.py
lima2/conductor/tango/utils.py
lima2/conductor/webservice/__init__.py
lima2/conductor/webservice/acquisition.py
lima2/conductor/webservice/benchmark.py
lima2/conductor/webservice/cli.py
lima2/conductor/webservice/detector.py
lima2/conductor/webservice/main.py
lima2/conductor/webservice/pipeline.py
lima2/conductor/webservice/utils.py
lima2/conductor/webservice/webapp.py
lima2/conductor/webservice/benchmark_generators/__init__.py
lima2/conductor/webservice/benchmark_generators/rois.py
lima2_client-4.1.3.dist-info/licenses/LICENSE
lima2_client-4.1.3.dist-info/METADATA
lima2_client-4.1.3.dist-info/WHEEL
lima2_client-4.1.3.dist-info/entry_points.txt
lima2_client-4.1.3.dist-info/top_level.txt
lima2_client-4.1.3.dist-info/RECORD
