Metadata-Version: 2.4
Name: lima2-client
Version: 4.1.3
Summary: The Python client library of the Lima2 system
Author: BCU (ESRF)
License-Expression: MIT
Project-URL: Repository, https://gitlab.esrf.fr/limagroup/lima2-client
Project-URL: Documentation, https://limagroup.gitlab-pages.esrf.fr/lima2-client/
Classifier: Intended Audience :: Science/Research
Classifier: Programming Language :: Python :: 3
Requires-Python: >=3.10
License-File: LICENSE
Requires-Dist: h5py
Requires-Dist: numpy
Requires-Dist: packaging
Requires-Dist: pytango
Requires-Dist: requests
Provides-Extra: conductor
Requires-Dist: jsonschema-default; extra == "conductor"
Requires-Dist: jsonschema-rs; extra == "conductor"
Requires-Dist: orjson; extra == "conductor"
Requires-Dist: starlette; extra == "conductor"
Requires-Dist: typer; extra == "conductor"
Requires-Dist: uvicorn[standard]; extra == "conductor"
Provides-Extra: shell
Requires-Dist: ipython; extra == "shell"
Requires-Dist: termcolor; extra == "shell"
Requires-Dist: typer; extra == "shell"
Provides-Extra: dev
Requires-Dist: black==22.3; extra == "dev"
Requires-Dist: flake8; extra == "dev"
Requires-Dist: httpx; extra == "dev"
Requires-Dist: lima2-client[conductor]; extra == "dev"
Requires-Dist: lima2-client[shell]; extra == "dev"
Requires-Dist: mypy; extra == "dev"
Requires-Dist: nosqltangodb; extra == "dev"
Requires-Dist: pytest; extra == "dev"
Requires-Dist: pytest-asyncio; extra == "dev"
Requires-Dist: pytest-cov; extra == "dev"
Requires-Dist: requests-mock; extra == "dev"
Requires-Dist: types-requests; extra == "dev"
Provides-Extra: docs
Requires-Dist: mkdocs; extra == "docs"
Requires-Dist: markdown-include; extra == "docs"
Requires-Dist: mkdocs-material; extra == "docs"
Requires-Dist: mkdocstrings[python]; extra == "docs"
Requires-Dist: pygments; extra == "docs"
Dynamic: license-file
